{
    "questions" : [
		{
			"question_text": "charles babbage invented the computer.",
			"options": [
				{
					"option_text" : "True",
					"is_correct" : true,
					"option_feedback": "correct answer"

				},
				{
					"option_text" : "False",
					"is_correct" : false,
					"option_feedback": "wrong answer"

				}
			],
			"hints" : [
				"try to remember the first introduction class."
			]

		},
		{
			"question_text": "Mahatma Gandhi is the father our nation.",
			"options": [
				{
					"option_text" : "True",
					"is_correct" : true,
					"option_feedback": "correct answer"

				},
				{
					"option_text" : "False",
					"is_correct" : false,
					"option_feedback": "wrong answer"

				}
			],
			"hints" : [
				"try to remember the first page in the testbook."
			]

		},
		{
			"question_text": "Who wrote the national Anthem?",
			"options": [
				{
					"option_text" : "Tagore",
					"is_correct" : true,
					"option_feedback": "correct answer"

				},
				{
					"option_text" : "Tyagaraju",
					"is_correct" : false,
					"option_feedback": "wrong answer"

				}
			],
			"hints" : [
				"try to remember the first page in the testbook."
			]

		},
		{
			"question_text": "Delhi is the capital of India.",
			"options": [
				{
					"option_text" : "True",
					"is_correct" : true,
					"option_feedback": "correct answer"

				},
				{
					"option_text" : "False",
					"is_correct" : false,
					"option_feedback": "wrong answer"

				}
			],
			"hints" : [
				"try to remember the first page in the testbook."
			]

		}
	]
}